pyail/__init__.py
pyail/api.py
pyail/core.py
pyail/exceptions.py
pyail-0.0.8.dist-info/LICENSE
pyail-0.0.8.dist-info/METADATA
pyail-0.0.8.dist-info/WHEEL
pyail-0.0.8.dist-info/RECORD
