Metadata-Version: 2.1
Name: pyail
Version: 0.0.8
Summary: 
Home-page: https://github.com/ail-project/PyAIL
License: BSD-2-Clause
Author: Aurelien Thirion (terrtia)
Author-email: aurelien.thirion@circl.lu
Requires-Python: >=3.6,<4.0
Classifier: License :: OSI Approved :: BSD License
Classifier: Programming Language :: Python :: 3
Classifier: Programming Language :: Python :: 3.6
Classifier: Programming Language :: Python :: 3.7
Classifier: Programming Language :: Python :: 3.8
Classifier: Programming Language :: Python :: 3.9
Classifier: Programming Language :: Python :: 3.10
Classifier: Programming Language :: Python :: 3.11
Classifier: Programming Language :: Python :: 3.12
Requires-Dist: requests (>=2.23.0,<3.0.0)
Project-URL: Repository, https://github.com/ail-project/PyAIL
